{"dictNodes":{"0":{"actionTarget":null,"actionName":"","name":null,"next":"23282","tru":"True","index":"0","posX":"-0.7196652","posY":"0.6089469","minimized":"False","advance_mode":"Instantly","type":"action"},"23282":{"action":"play_sound","clipName":"Cheering and clapping","volume":"1","name":null,"next":"23283","tru":"True","index":"23282","posX":"3.372957","posY":"1.063752","minimized":"False","advance_mode":"WhenCompleted","type":"sound"},"23283":{"content":"This is the end of the study. Thanks for your participation!","owner":null,"speaking":"True","name":"Dialogue State","next":"23284","tru":"True","index":"23283","posX":"7.321887","posY":"2.072514","minimized":"False","advance_mode":"OnClick","type":"dialogue"},"23284":{"nextScript":"","transitionText":"None","variablePairs":"","name":"End Sticker","next":"-1","tru":"True","index":"23284","posX":"10.84024","posY":"3.025915","minimized":"False","advance_mode":"OnClick","type":"end"}},"scene":{"name":"Scene 1","title":"end","pos":{"x":0,"y":0,"z":0},"uid":"6","background":"creditsBackground","furniture":[{"uid":0,"rotation":0,"visible":true,"locked":true,"color":"FFFFFF","textcolor":"000000","image":"creditsBackground","value":0,"text":"","fontSize":0,"parentName":"","objectType":0,"name":"Background","pos":{"x":0,"y":0,"z":0},"size":{"x":960,"y":540}}],"layoutScale":0.5,"layoutPosition":{"x":0,"y":0},"scriptorScale":0.4793388,"scriptorPosition":{"x":-50.85745,"y":19.0567074},"layoutParamSet":true,"scriptorParamSet":true},"started":false}